scaffolder/__init__.py
scaffolder/cli.py
scaffolder/core.py
scaffolder/gui.py
scai_tool-1.0.0.dist-info/METADATA
scai_tool-1.0.0.dist-info/WHEEL
scai_tool-1.0.0.dist-info/entry_points.txt
scai_tool-1.0.0.dist-info/top_level.txt
scai_tool-1.0.0.dist-info/RECORD
