Metadata-Version: 2.4
Name: scai-tool
Version: 1.0.0
Summary: A developer tool that turns AI-generated directory tree text into actual files and folders.
Home-page: https://github.com/kaus-04/scai
Author: kaus-04
Author-email: kaus77135@gmail.com
License: MIT
Classifier: License :: OSI Approved :: MIT License
Classifier: Programming Language :: Python :: 3
Classifier: Operating System :: OS Independent
Requires-Python: >=3.6
Dynamic: author
Dynamic: author-email
Dynamic: classifier
Dynamic: description
Dynamic: description-content-type
Dynamic: home-page
Dynamic: license
Dynamic: requires-python
Dynamic: summary
